openearth/__init__.py
openearth/client.py
openearth-0.1.3.dist-info/METADATA
openearth-0.1.3.dist-info/WHEEL
openearth-0.1.3.dist-info/top_level.txt
openearth-0.1.3.dist-info/RECORD
