Metadata-Version: 2.4
Name: openearth
Version: 0.1.3
Summary: Python client for the OpenEarth API
Author: Sanjana Y
License: Proprietary
Project-URL: Docs, https://example.com/docs
Requires-Python: >=3.11
Requires-Dist: httpx>=0.27.0
